py-ele-1/Person.py
py-ele-1/__init__.py
py_ele_1/Person.py
py_ele_1/__init__.py
py_ele_1-1.0.8.dist-info/METADATA
py_ele_1-1.0.8.dist-info/WHEEL
py_ele_1-1.0.8.dist-info/top_level.txt
py_ele_1-1.0.8.dist-info/RECORD
